zenodo_client/__init__.py
zenodo_client/__main__.py
zenodo_client/api.py
zenodo_client/cli.py
zenodo_client/py.typed
zenodo_client/struct.py
zenodo_client/version.py
zenodo_client-0.4.2.dist-info/licenses/LICENSE
zenodo_client-0.4.2.dist-info/WHEEL
zenodo_client-0.4.2.dist-info/entry_points.txt
zenodo_client-0.4.2.dist-info/METADATA
zenodo_client-0.4.2.dist-info/RECORD
